shearletvit/__init__.py
shearletvit-0.0.0.dist-info/METADATA
shearletvit-0.0.0.dist-info/WHEEL
shearletvit-0.0.0.dist-info/licenses/LICENSE
shearletvit-0.0.0.dist-info/RECORD
