Metadata-Version: 2.4
Name: ShearletViT
Version: 0.0.0
Summary: Digital Shearlet Bank Vision (3D) Transformer
Project-URL: Homepage, https://github.com/kkt-ee/ShearletViT
Project-URL: Issues, https://github.com/kkt-ee/ShearletViT/issues
Author-email: Kishore Kumar Tarafdar <kkt.ee.ai@gmail.com>
License-Expression: GPL-3.0-or-later
License-File: LICENSE
Classifier: Intended Audience :: Science/Research
Classifier: Operating System :: OS Independent
Classifier: Programming Language :: Python :: 3
Classifier: Topic :: Scientific/Engineering
Requires-Python: >=3.9
